{
    "count":4,
    "time":"דקה ו20 שניות",
    "timeSec":80000,
    "1":["החוקר _____ נתונים חשובים בנוגע לשינויי האקלים.",
        "(1) מבזבז",
        "(2) מפיץ",
        "(3) שוכח",
        "(4) אוסף"],
    "answer_1":4,
    "des_1":["نبحث عن فعل يدل على جمع المعلومات.","החוקר אוסף נתונים חשובים בנוגע לשינויי האקלים.","يقوم الباحث بجمع بيانات مهمة فيما يتعلق بتغير المناخ."],

    "2":["הסרט _____ תגובות חיוביות מהקהל והמבקרים.",
        "(1) קיבל",
        "(2) נדחה",
        "(3) בוטל",
        "(4) שודר"],
    "answer_2":1,
    "des_2":["نبحث عن فعل يدل على تلقي ردود الفعل.","הסרט קיבל תגובות חיוביות מהקהל והמבקרים.","الفيلم حصل على ردود فعل إيجابية من الجمهور والنقاد."],

    "3":["ההיסטוריה של המקום _____ של סודות ורגשות.",
        "(1) מפריעה",
        "(2) משאירה",
        "(3) מוחקת",
        "(4) מכילה"],
    "answer_3":4,
    "des_3":["نبحث عن فعل يدل على احتواء السجلات.","ההיסטוריה של המקום מכילה של סודות ורגשות.","تاريخ المكان يحتوي على أسرار وعواطف."],

    "4":["הספורטאי _____ את התחרות עם תוצאה מרשימה.",
        "(1) ניצח",
        "(2) הפסיד",
        "(3) שקע",
        "(4) נטש"],
    "answer_4":1,
    "des_4":["نبحث عن فعل يدل على الفوز.","הספורטאי ניצח את התחרות עם תוצאה מרשימה.","الرياضي فاز في المنافسة بنتيجة رائعة."],

    "5":["האדריכל _____ את הבניין בצורה חדשנית.",
        "(1) הרס",
        "(2) תכנן",
        "(3) בנה",
        "(4) שיפץ"],
    "answer_5":2,
    "des_5":["نبحث عن فعل يدل على تصميم أو إنشاء.","האדריכל תכנן את הבניין בצורה חדשנית.","المهندس المعماري صمم المبنى بطريقة مبتكرة."],

    "6":["ההחלטה נלקחה לאחר _____ של שיחות ארוכות.",
        "(1) חיפוש",
        "(2) חיסול",
        "(3) סבב",
        "(4) הפסקה"],
    "answer_6":3,
    "des_6":["نبحث عن كلمة تشير إلى عملية أخذ القرار","ההחלטה נלקחה לאחר סבב של שיחות ארוכות.","تم اتخاذ القرار بعد دورة من المحادثات الطويلة."],

    "7":["המשטרה _____ חקירה בעקבות האירוע.",
        "(1) סגרה",
        "(2) ערכה",
        "(3) עצרה",
        "(4) פתחה"],
    "answer_7":4,
    "des_7":["نبحث عن فعل يدل على بدء التحقيق.","המשטרה פתחה חקירה בעקבות האירוע.","فتحت الشرطة تحقيقًا بعد الحدث."],

    "8":["הסופר _____ את הדמויות כך שיראו מציאותיות",
        "(1) הזניח",
        "(2) השמיד",
        "(3) פיתח",
        "(4) שיבש"],
    "answer_8":3,
    "des_8":["نبحث عن فعل يدل على تحسين أو إبداع الشخصيات.","הסופר פיתח את הדמויות כך שיראו מציאותיות.","قام المؤلف بتطوير الشخصيات بحيث تبدو واقعية."],

    "9":["המנכ''ל _____ את החברה לשיאים חדשים בשנה האחרונה.",
        "(1) הוביל",
        "(2) הזניח",
        "(3) הפריע",
        "(4) נטש"],
    "answer_9":1,
    "des_9":["نبحث عن فعل يدل على القيادة والنجاح.","המנכ''ל הוביל את החברה לשיאים חדשים בשנה האחרונה.","قاد الرئيس التنفيذي الشركة إلى آفاق جديدة في العام الماضي."]

}